README.rst
setup.py
ktcal2/__init__.py
ktcal2/api.py
ktcal2/kt_cal2.py
ktcal2.egg-info/PKG-INFO
ktcal2.egg-info/SOURCES.txt
ktcal2.egg-info/dependency_links.txt
ktcal2.egg-info/entry_points.txt
ktcal2.egg-info/requires.txt
ktcal2.egg-info/top_level.txt
ktcal2/lib/__init__.py
ktcal2/lib/data.py
ktcal2/lib/ssh_brute.py