Metadata-Version: 1.1
Name: ktcal2
Version: 0.1.5
Summary: SSH brute forcer tool and library, using AsyncIO of Python 3.4
Home-page: https://github.com/cr0hn/ktcal2
Author: cr0hn
Author-email: cr0hn<-at->cr0hn.com
License: BSD
Platform: UNKNOWN
Classifier: Environment :: Console
Classifier: Intended Audience :: System Administrators
Classifier: Intended Audience :: Other Audience
Classifier: License :: OSI Approved :: BSD License
Classifier: Operating System :: MacOS
Classifier: Operating System :: Microsoft :: Windows
Classifier: Operating System :: POSIX
Classifier: Programming Language :: Python :: 3
Classifier: Topic :: Security
